voiceassistant/__init__.py
voiceassistant/__main__.py
voiceassistant/config.py
voiceassistant/const.py
voiceassistant/core.py
voiceassistant/exceptions.py
voiceassistant/setup.py
voiceassistant/version.py
voiceassistant/addons/__init__.py
voiceassistant/addons/create.py
voiceassistant/data/__init__.py
voiceassistant/data/audio/__init__.py
voiceassistant/data/audio/bamboo.mp3
voiceassistant/data/audio/click.mp3
voiceassistant/data/audio/dzin.mp3
voiceassistant/data/audio/maybe.mp3
voiceassistant/data/audio/now.mp3
voiceassistant/data/nlp/__init__.py
voiceassistant/data/nlp/regex.yaml
voiceassistant/data/sample_config/__init__.py
voiceassistant/data/sample_config/configuration.yaml
voiceassistant/data/sample_config/google_credentials.json
voiceassistant/integrations/__init__.py
voiceassistant/integrations/base.py
voiceassistant/integrations/general.py
voiceassistant/integrations/respeaker.py
voiceassistant/integrations/skills.py
voiceassistant/integrations/hass/__init__.py
voiceassistant/integrations/hass/actions.py
voiceassistant/integrations/hass/const.py
voiceassistant/integrations/hass/skills.py
voiceassistant/integrations/hass/utils.py
voiceassistant/integrations/spotify/__init__.py
voiceassistant/integrations/spotify/client.py
voiceassistant/integrations/spotify/const.py
voiceassistant/interfaces/__init__.py
voiceassistant/interfaces/base.py
voiceassistant/interfaces/http/__init__.py
voiceassistant/interfaces/http/api_app.py
voiceassistant/interfaces/http/auth.py
voiceassistant/interfaces/speech/__init__.py
voiceassistant/interfaces/speech/keyword.py
voiceassistant/interfaces/speech/microphone_stream.py
voiceassistant/interfaces/speech/speech_to_text.py
voiceassistant/interfaces/speech/text_to_speech.py
voiceassistant/nlp/__init__.py
voiceassistant/nlp/base.py
voiceassistant/nlp/regex/__init__.py
voiceassistant/nlp/regex/expression.py
voiceassistant/skills/__init__.py
voiceassistant/skills/create.py
voiceassistant/utils/__init__.py
voiceassistant-0.11.0.dist-info/LICENSE
voiceassistant-0.11.0.dist-info/METADATA
voiceassistant-0.11.0.dist-info/WHEEL
voiceassistant-0.11.0.dist-info/entry_points.txt
voiceassistant-0.11.0.dist-info/top_level.txt
voiceassistant-0.11.0.dist-info/RECORD
