Metadata-Version: 2.1
Name: voiceassistant
Version: 0.11.0
Summary: Open-source customizable voice assistant
Home-page: https://github.com/vadimtitov/voice-assistant
Author: Vadim Titov
Author-email: titov.hse@gmail.com
Project-URL: Bug Tracker, https://github.com/vadimtitov/voice-assistant/issues
Classifier: Programming Language :: Python :: 3
Classifier: License :: OSI Approved :: MIT License
Classifier: Operating System :: OS Independent
Classifier: Development Status :: 3 - Alpha
Classifier: Topic :: Home Automation
Requires-Python: >=3.7
License-File: LICENSE
Requires-Dist: boto3 (<2,>=1.9.71)
Requires-Dist: google-cloud-speech (<3,>=2.2.0)
Requires-Dist: PyAudio (<1,>=0.2.11)
Requires-Dist: six (<2,>=1.11.0)
Requires-Dist: pyyaml (<6,>=5.4.1)
Requires-Dist: pvporcupine (<2,>=1.9.3)
Requires-Dist: iterators (==0.0.2)
Requires-Dist: hypothesis (<6,>=5.16.0)
Requires-Dist: hassapi (<1,>=0.1.1)
Requires-Dist: pixel-ring (==0.1.0)
Requires-Dist: flask (<3,>=2.0.1)
Requires-Dist: gpiozero (<2,>=1.6.2)
Requires-Dist: RPi.GPIO (==0.7.1)
Requires-Dist: diskcache (<6,>=5.2.1)
Requires-Dist: tekore (==4.3.0)
Requires-Dist: tenacity (<9,>=8.0.1)
Requires-Dist: pyalsaaudio (<1,>=0.9.0)
Provides-Extra: test
Requires-Dist: pytest ; extra == 'test'
